{
  "auditDate": "2026-01-24",
  "productionUrl": "https://tdrealtyohio.com",
  "googleAds": {
    "tagId": "AW-17866418952",
    "implementationMethod": "gtag.js",
    "loadedVia": "googletagmanager.com/gtag/js",
    "configEvents": ["config AW-17866418952"],
    "conversionLabels": [],
    "notes": "Google Ads tag is loaded on all pages. No conversion labels currently configured for form submissions or phone clicks."
  },
  "googleAnalytics": {
    "ga4MeasurementId": null,
    "gtmContainerId": null,
    "notes": "Site uses Google Ads tag directly (AW-). No separate GA4 or GTM implementation detected. Consider adding GA4 for enhanced analytics."
  },
  "metaPixel": {
    "pixelId": null,
    "notes": "No Meta/Facebook Pixel detected."
  },
  "thirdPartyScripts": [
    {
      "domain": "googletagmanager.com",
      "purpose": "Google Ads tracking",
      "loadOrder": "async in head"
    },
    {
      "domain": "fonts.googleapis.com",
      "purpose": "Google Fonts",
      "loadOrder": "preconnect + link in head"
    },
    {
      "domain": "fonts.gstatic.com",
      "purpose": "Google Fonts static assets",
      "loadOrder": "preconnect in head"
    },
    {
      "domain": "formspree.io",
      "purpose": "Form submission handling",
      "loadOrder": "runtime on form submit"
    }
  ],
  "currentEvents": {
    "pageview": true,
    "formSubmission": false,
    "phoneClick": false,
    "calculatorInteraction": false,
    "ctaClick": false,
    "mobileMenuOpen": false
  },
  "recommendedConversions": [
    {
      "name": "Phone Click",
      "trigger": "Click on tel: links",
      "value": "Dynamic (lead value)",
      "priority": "P0"
    },
    {
      "name": "Form Submission",
      "trigger": "Successful form submit (response.ok)",
      "value": "Dynamic (lead value)",
      "priority": "P0"
    },
    {
      "name": "Calculator Engagement",
      "trigger": "Slider interaction (debounced)",
      "value": "No monetary value",
      "priority": "P0"
    }
  ],
  "formsInventory": [
    {
      "formId": "contact-form",
      "page": "/contact/",
      "action": "https://formspree.io/f/mykkypyd",
      "method": "POST"
    },
    {
      "formId": "home-value-form",
      "page": "/home-value/",
      "action": "https://formspree.io/f/mykkypyd",
      "method": "POST"
    },
    {
      "formId": "agent-form",
      "page": "/agents/",
      "action": "https://formspree.io/f/mykkypyd",
      "method": "POST"
    },
    {
      "formId": "referral-form",
      "page": "/referrals/",
      "action": "https://formspree.io/f/mykkypyd",
      "method": "POST"
    }
  ]
}
